{"word_count": 16202, "processed_language": "en", "personality": [{"trait_id": "big5_openness", "name": "Openness", "category": "personality", "percentile": 0.9819013680533232, "raw_score": 0.8155289825589701, "significant": true, "children": [{"trait_id": "facet_adventurousness", "name": "Adventurousness", "category": "personality", "percentile": 0.676306417002825, "raw_score": 0.5210853872665193, "significant": true}, {"trait_id": "facet_artistic_interests", "name": "Artistic interests", "category": "personality", "percentile": 0.3342363210229726, "raw_score": 0.6436455302283616, "significant": true}, {"trait_id": "facet_emotionality", "name": "Emotionality", "category": "personality", "percentile": 0.006815990492374413, "raw_score": 0.5476258989111753, "significant": true}, {"trait_id": "facet_imagination", "name": "Imagination", "category": "personality", "percentile": 0.4607260468512049, "raw_score": 0.7299609820911201, "significant": true}, {"trait_id": "facet_intellect", "name": "Intellect", "category": "personality", "percentile": 0.9981593778575969, "raw_score": 0.7416761969143333, "significant": true}, {"trait_id": "facet_liberalism", "name": "Authority-challenging", "category": "personality", "percentile": 0.8968759172822136, "raw_score": 0.5798900116696101, "significant": true}]}, {"trait_id": "big5_conscientiousness", "name": "Conscientiousness", "category": "personality", "percentile": 0.2989494948075542, "raw_score": 0.6034514870823684, "significant": true, "children": [{"trait_id": "facet_achievement_striving", "name": "Achievement striving", "category": "personality", "percentile": 0.5013539674255075, "raw_score": 0.6885781419870786, "significant": true}, {"trait_id": "facet_cautiousness", "name": "Cautiousness", "category": "personality", "percentile": 0.8370067318044985, "raw_score": 0.5544773443805734, "significant": true}, {"trait_id": "facet_dutifulness", "name": "Dutifulness", "category": "personality", "percentile": 0.23922684523287063, "raw_score": 0.641542349315359, "significant": true}, {"trait_id": "facet_orderliness", "name": "Orderliness", "category": "personality", "percentile": 0.31968769064421587, "raw_score": 0.4788074996715573, "significant": true}, {"trait_id": "facet_self_discipline", "name": "Self-discipline", "category": "personality", "percentile": 0.3928361523477925, "raw_score": 0.5576995258207497, "significant": true}, {"trait_id": "facet_self_efficacy", "name": "Self-efficacy", "category": "personality", "percentile": 0.579857731493492, "raw_score": 0.7601871510254679, "significant": true}]}, {"trait_id": "big5_extraversion", "name": "Extraversion", "category": "personality", "percentile": 0.1741827708663869, "raw_score": 0.5091597469001523, "significant": true, "children": [{"trait_id": "facet_activity_level", "name": "Activity level", "category": "personality", "percentile": 0.699232794693855, "raw_score": 0.5670994145673885, "significant": true}, {"trait_id": "facet_assertiveness", "name": "Assertiveness", "category": "personality", "percentile": 0.49716021051648485, "raw_score": 0.6437029180721134, "significant": true}, {"trait_id": "facet_cheerfulness", "name": "Cheerfulness", "category": "personality", "percentile": 0.00026141509769656013, "raw_score": 0.5017290981694278, "significant": true}, {"trait_id": "facet_excitement_seeking", "name": "Excitement-seeking", "category": "personality", "percentile": 0.07595271104209106, "raw_score": 0.5428520396321881, "significant": true}, {"trait_id": "facet_friendliness", "name": "Outgoing", "category": "personality", "percentile": 0.00974961509423361, "raw_score": 0.4433329338408893, "significant": true}, {"trait_id": "facet_gregariousness", "name": "Gregariousness", "category": "personality", "percentile": 0.0007806608155143668, "raw_score": 0.29073002144229665, "significant": true}]}, {"trait_id": "big5_agreeableness", "name": "Agreeableness", "category": "personality", "percentile": 0.0004460323777945585, "raw_score": 0.6101128910593915, "significant": true, "children": [{"trait_id": "facet_altruism", "name": "Altruism", "category": "personality", "percentile": 0.054944677536111874, "raw_score": 0.6490062395081486, "significant": true}, {"trait_id": "facet_cooperation", "name": "Cooperation", "category": "personality", "percentile": 0.5289870958236478, "raw_score": 0.5837705435831104, "significant": true}, {"trait_id": "facet_modesty", "name": "Modesty", "category": "personality", "percentile": 0.10342566328472641, "raw_score": 0.38176992004868804, "significant": true}, {"trait_id": "facet_morality", "name": "Uncompromising", "category": "personality", "percentile": 0.5237571996607147, "raw_score": 0.6286224062640308, "significant": true}, {"trait_id": "facet_sympathy", "name": "Sympathy", "category": "personality", "percentile": 0.2820825798872597, "raw_score": 0.6414585416134047, "significant": true}, {"trait_id": "facet_trust", "name": "Trust", "category": "personality", "percentile": 0.48688003977724914, "raw_score": 0.5844467054893097, "significant": true}]}, {"trait_id": "big5_neuroticism", "name": "Emotional range", "category": "personality", "percentile": 0.9235303466086808, "raw_score": 0.5479337479857235, "significant": true, "children": [{"trait_id": "facet_anger", "name": "Fiery", "category": "personality", "percentile": 0.6318780948721799, "raw_score": 0.5541354148874665, "significant": true}, {"trait_id": "facet_anxiety", "name": "Prone to worry", "category": "personality", "percentile": 0.17082679625218344, "raw_score": 0.5292630778639069, "significant": true}, {"trait_id": "facet_depression", "name": "Melancholy", "category": "personality", "percentile": 0.8384521733980485, "raw_score": 0.5110242559329308, "significant": true}, {"trait_id": "facet_immoderation", "name": "Immoderation", "category": "personality", "percentile": 0.09501928844557117, "raw_score": 0.45022519081568496, "significant": true}, {"trait_id": "facet_self_consciousness", "name": "Self-consciousness", "category": "personality", "percentile": 0.9294687585441095, "raw_score": 0.6241622259449855, "significant": true}, {"trait_id": "facet_vulnerability", "name": "Susceptible to stress", "category": "personality", "percentile": 0.5202776631727062, "raw_score": 0.47086157012268576, "significant": true}]}], "needs": [{"trait_id": "need_challenge", "name": "Challenge", "category": "needs", "percentile": 0.40659071578362976, "raw_score": 0.721185554097403, "significant": true}, {"trait_id": "need_closeness", "name": "Closeness", "category": "needs", "percentile": 0.0003934752333844549, "raw_score": 0.6443401690891882, "significant": true}, {"trait_id": "need_curiosity", "name": "Curiosity", "category": "needs", "percentile": 0.9349792403702968, "raw_score": 0.8564956059621425, "significant": true}, {"trait_id": "need_excitement", "name": "Excitement", "category": "needs", "percentile": 0.13391152006397244, "raw_score": 0.5971833044624716, "significant": true}, {"trait_id": "need_harmony", "name": "Harmony", "category": "needs", "percentile": 0.004240692484246744, "raw_score": 0.7183646797091341, "significant": true}, {"trait_id": "need_ideal", "name": "Ideal", "category": "needs", "percentile": 0.3177607460884675, "raw_score": 0.6685305263428255, "significant": true}, {"trait_id": "need_liberty", "name": "Liberty", "category": "needs", "percentile": 0.43301530895328466, "raw_score": 0.7301917076605263, "significant": true}, {"trait_id": "need_love", "name": "Love", "category": "needs", "percentile": 0.0007354814341287153, "raw_score": 0.6139493502466837, "significant": true}, {"trait_id": "need_practicality", "name": "Practicality", "category": "needs", "percentile": 0.8293379983486455, "raw_score": 0.7483321416635901, "significant": true}, {"trait_id": "need_self_expression", "name": "Self-expression", "category": "needs", "percentile": 0.08172807492767786, "raw_score": 0.6269674800857299, "significant": true}, {"trait_id": "need_stability", "name": "Stability", "category": "needs", "percentile": 0.003151309940183422, "raw_score": 0.6474554969162986, "significant": true}, {"trait_id": "need_structure", "name": "Structure", "category": "needs", "percentile": 0.4649885082382452, "raw_score": 0.6936974521522028, "significant": true}], "values": [{"trait_id": "value_conservation", "name": "Conservation", "category": "values", "percentile": 4.731634022386855e-05, "raw_score": 0.4895763292470211, "significant": true}, {"trait_id": "value_openness_to_change", "name": "Openness to change", "category": "values", "percentile": 0.3445348785325904, "raw_score": 0.7688391165771334, "significant": true}, {"trait_id": "value_hedonism", "name": "Hedonism", "category": "values", "percentile": 0.048379268442483137, "raw_score": 0.6320688056751637, "significant": true}, {"trait_id": "value_self_enhancement", "name": "Self-enhancement", "category": "values", "percentile": 0.08614708006748406, "raw_score": 0.646450827501948, "significant": true}, {"trait_id": "value_self_transcendence", "name": "Self-transcendence", "category": "values", "percentile": 0.07933667072321782, "raw_score": 0.8100004438254127, "significant": true}], "consumption_preferences": [{"consumption_preference_category_id": "consumption_preferences_shopping", "name": "Purchasing Preferences", "consumption_preferences": [{"consumption_preference_id": "consumption_preferences_automobile_ownership_cost", "name": "Likely to be sensitive to ownership cost when buying automobiles", "score": 1.0}, {"consumption_preference_id": "consumption_preferences_automobile_safety", "name": "Likely to prefer safety when buying automobiles", "score": 0.0}, {"consumption_preference_id": "consumption_preferences_clothes_quality", "name": "Likely to prefer quality when buying clothes", "score": 1.0}, {"consumption_preference_id": "consumption_preferences_clothes_style", "name": "Likely to prefer style when buying clothes", "score": 0.0}, {"consumption_preference_id": "consumption_preferences_clothes_comfort", "name": "Likely to prefer comfort when buying clothes", "score": 1.0}, {"consumption_preference_id": "consumption_preferences_influence_brand_name", "name": "Likely to be influenced by brand name when making product purchases", "score": 0.0}, {"consumption_preference_id": "consumption_preferences_influence_utility", "name": "Likely to be influenced by product utility when making product purchases", "score": 0.5}, {"consumption_preference_id": "consumption_preferences_influence_online_ads", "name": "Likely to be influenced by online ads when making product purchases", "score": 0.0}, {"consumption_preference_id": "consumption_preferences_influence_social_media", "name": "Likely to be influenced by social media when making product purchases", "score": 0.0}, {"consumption_preference_id": "consumption_preferences_influence_family_members", "name": "Likely to be influenced by family when making product purchases", "score": 0.0}, {"consumption_preference_id": "consumption_preferences_spur_of_moment", "name": "Likely to indulge in spur of the moment purchases", "score": 0.0}, {"consumption_preference_id": "consumption_preferences_credit_card_payment", "name": "Likely to prefer using credit cards for shopping", "score": 1.0}]}, {"consumption_preference_category_id": "consumption_preferences_health_and_activity", "name": "Health & Activity Preferences", "consumption_preferences": [{"consumption_preference_id": "consumption_preferences_eat_out", "name": "Likely to eat out frequently", "score": 0.0}, {"consumption_preference_id": "consumption_preferences_gym_membership", "name": "Likely to have a gym membership", "score": 0.0}, {"consumption_preference_id": "consumption_preferences_outdoor", "name": "Likely to like outdoor activities", "score": 0.5}]}, {"consumption_preference_category_id": "consumption_preferences_environmental_concern", "name": "Environmental Concern Preferences", "consumption_preferences": [{"consumption_preference_id": "consumption_preferences_concerned_environment", "name": "Likely to be concerned about the environment", "score": 1.0}]}, {"consumption_preference_category_id": "consumption_preferences_entrepreneurship", "name": "Entrepreneurship Preferences", "consumption_preferences": [{"consumption_preference_id": "consumption_preferences_start_business", "name": "Likely to consider starting a business in next few years", "score": 0.5}]}, {"consumption_preference_category_id": "consumption_preferences_movie", "name": "Movie Preferences", "consumption_preferences": [{"consumption_preference_id": "consumption_preferences_movie_romance", "name": "Likely to like romance movies", "score": 0.0}, {"consumption_preference_id": "consumption_preferences_movie_adventure", "name": "Likely to like adventure movies", "score": 1.0}, {"consumption_preference_id": "consumption_preferences_movie_horror", "name": "Likely to like horror movies", "score": 0.0}, {"consumption_preference_id": "consumption_preferences_movie_musical", "name": "Likely to like musical movies", "score": 0.0}, {"consumption_preference_id": "consumption_preferences_movie_historical", "name": "Likely to like historical movies", "score": 1.0}, {"consumption_preference_id": "consumption_preferences_movie_science_fiction", "name": "Likely to like science-fiction movies", "score": 1.0}, {"consumption_preference_id": "consumption_preferences_movie_war", "name": "Likely to like war movies", "score": 1.0}, {"consumption_preference_id": "consumption_preferences_movie_drama", "name": "Likely to like drama movies", "score": 0.0}, {"consumption_preference_id": "consumption_preferences_movie_action", "name": "Likely to like action movies", "score": 1.0}, {"consumption_preference_id": "consumption_preferences_movie_documentary", "name": "Likely to like documentary movies", "score": 1.0}]}, {"consumption_preference_category_id": "consumption_preferences_music", "name": "Music Preferences", "consumption_preferences": [{"consumption_preference_id": "consumption_preferences_music_rap", "name": "Likely to like rap music", "score": 0.5}, {"consumption_preference_id": "consumption_preferences_music_country", "name": "Likely to like country music", "score": 0.5}, {"consumption_preference_id": "consumption_preferences_music_r_b", "name": "Likely to like R&B music", "score": 0.5}, {"consumption_preference_id": "consumption_preferences_music_hip_hop", "name": "Likely to like hip hop music", "score": 0.0}, {"consumption_preference_id": "consumption_preferences_music_live_event", "name": "Likely to attend live musical events", "score": 0.0}, {"consumption_preference_id": "consumption_preferences_music_playing", "name": "Likely to have experience playing music", "score": 1.0}, {"consumption_preference_id": "consumption_preferences_music_latin", "name": "Likely to like Latin music", "score": 1.0}, {"consumption_preference_id": "consumption_preferences_music_rock", "name": "Likely to like rock music", "score": 1.0}, {"consumption_preference_id": "consumption_preferences_music_classical", "name": "Likely to like classical music", "score": 0.5}]}, {"consumption_preference_category_id": "consumption_preferences_reading", "name": "Reading Preferences", "consumption_preferences": [{"consumption_preference_id": "consumption_preferences_read_frequency", "name": "Likely to read often", "score": 1.0}, {"consumption_preference_id": "consumption_preferences_books_entertainment_magazines", "name": "Likely to read entertainment magazines", "score": 0.0}, {"consumption_preference_id": "consumption_preferences_books_non_fiction", "name": "Likely to read non-fiction books", "score": 1.0}, {"consumption_preference_id": "consumption_preferences_books_financial_investing", "name": "Likely to read financial investment books", "score": 1.0}, {"consumption_preference_id": "consumption_preferences_books_autobiographies", "name": "Likely to read autobiographical books", "score": 0.0}]}, {"consumption_preference_category_id": "consumption_preferences_volunteering", "name": "Volunteering Preferences", "consumption_preferences": [{"consumption_preference_id": "consumption_preferences_volunteer", "name": "Likely to volunteer for social causes", "score": 0.0}]}], "warnings": []}